example_package_bhrutledge/__init__.py
example_package_bhrutledge/example.py
example_package_bhrutledge-0.0.1.post1.dist-info/METADATA
example_package_bhrutledge-0.0.1.post1.dist-info/WHEEL
example_package_bhrutledge-0.0.1.post1.dist-info/licenses/LICENSE
example_package_bhrutledge-0.0.1.post1.dist-info/RECORD
